README.md
setup.py
bert_seq2seq/__init__.py
bert_seq2seq/bart_chinese.py
bert_seq2seq/basic_bert.py
bert_seq2seq/bert_cls_classifier.py
bert_seq2seq/bert_cls_multi_classifier.py
bert_seq2seq/bert_cls_multi_seq2seq.py
bert_seq2seq/bert_relation_extraction.py
bert_seq2seq/bert_seq_labeling.py
bert_seq2seq/bert_seq_labeling_crf.py
bert_seq2seq/config.py
bert_seq2seq/dataset.py
bert_seq2seq/extend_model_method.py
bert_seq2seq/gpt2_generate_model.py
bert_seq2seq/helper.py
bert_seq2seq/seq2seq_model.py
bert_seq2seq/simbert_model.py
bert_seq2seq/t5_ch.py
bert_seq2seq/tokenizer.py
bert_seq2seq/utils.py
bert_seq2seq.egg-info/PKG-INFO
bert_seq2seq.egg-info/SOURCES.txt
bert_seq2seq.egg-info/dependency_links.txt
bert_seq2seq.egg-info/top_level.txt
bert_seq2seq/model/__init__.py
bert_seq2seq/model/bart_model.py
bert_seq2seq/model/bert_model.py
bert_seq2seq/model/crf.py
bert_seq2seq/model/gpt2_model.py
bert_seq2seq/model/nezha_model.py
bert_seq2seq/model/roberta_model.py
bert_seq2seq/model/t5_model.py
state_dict/__init__.py
state_dict/bert_english_autotitle.py
state_dict/bert_seq2seq_save/__init__.py
state_dict/bert_seq2seq_save/basic_bert.py
state_dict/bert_seq2seq_save/bert_cls_classifier.py
state_dict/bert_seq2seq_save/bert_relation_extraction.py
state_dict/bert_seq2seq_save/bert_seq_labeling.py
state_dict/bert_seq2seq_save/bert_seq_labeling_crf.py
state_dict/bert_seq2seq_save/config.py
state_dict/bert_seq2seq_save/extend_model_method.py
state_dict/bert_seq2seq_save/gpt2_generate_model.py
state_dict/bert_seq2seq_save/seq2seq_model.py
state_dict/bert_seq2seq_save/simbert_model.py
state_dict/bert_seq2seq_save/t5_ch.py
state_dict/bert_seq2seq_save/tokenizer.py
state_dict/bert_seq2seq_save/tokenizer_test.py
state_dict/bert_seq2seq_save/utils.py
state_dict/bert_seq2seq_save/model/__init__.py
state_dict/bert_seq2seq_save/model/bart_model.py
state_dict/bert_seq2seq_save/model/bert_model.py
state_dict/bert_seq2seq_save/model/crf.py
state_dict/bert_seq2seq_save/model/gpt2_model.py
state_dict/bert_seq2seq_save/model/roberta_model.py
state_dict/bert_seq2seq_save/model/t5_model.py