Metadata-Version: 1.0
Name: bert-seq2seq
Version: 2.3.5
Summary: use torch to do bert_seq2seq task
Home-page: https://github.com/920232796/bert_seq2seq
Author: xingzhaohu
Author-email: 920232796@qq.com
License: Apache License 2.0
Platform: UNKNOWN
